src/config.py
src/function_analysis/README.md
src/function_analysis/__init__.py
src/function_analysis/cli/__init__.py
src/function_analysis/cli/indexer.py
src/function_analysis/config/__init__.py
src/function_analysis/config/settings.py
src/function_analysis/core/__init__.py
src/function_analysis/core/clang_parser.py
src/function_analysis/core/graph2vec.py
src/function_analysis/core/graph_converter.py
src/function_analysis/core/models.py
src/function_analysis/fnToCommand.json
src/function_analysis/interfaces/__init__.py
src/function_analysis/interfaces/api.py
src/function_analysis/interfaces/chat.py
src/function_analysis/interfaces/function_tool.py
src/function_analysis/run_api.py
src/function_analysis/storage/__init__.py
src/function_analysis/storage/redis_client.py
src/function_analysis/storage/vector_search.py
src/function_analysis/tests/__init__.py
src/function_analysis/tests/test_clang_parser.py
src/github_client/client.py
src/github_client/models.py
src/main.py
src/mcp_server.py
src/notifications/__init__.py
src/notifications/slack.py
src/notifications/tool.py
src/profiling/__init__.py
src/profiling/cli/__init__.py
src/profiling/cli/profile_indexer.py
src/profiling/interfaces/__init__.py
src/profiling/interfaces/profiling_tool.py
src/profiling/models.py
src/profiling/parsers/__init__.py
src/profiling/parsers/perf_parser.py
src/profiling/queries/__init__.py
src/profiling/queries/profile_queries.py
src/profiling/queries/sqlite_queries.py
src/profiling/queries/sqlite_queries_old.py
src/profiling/storage/__init__.py
src/profiling/storage/profile_storage.py
src/profiling/storage/sqlite_schema.sql
src/profiling/storage/sqlite_storage.py
redopt-0.1.0.dist-info/METADATA
redopt-0.1.0.dist-info/WHEEL
redopt-0.1.0.dist-info/entry_points.txt
redopt-0.1.0.dist-info/RECORD
