Metadata-Version: 2.1
Name: redopt
Version: 0.1.0
Summary: AI tool to connect Redis OSS source code, benchmarks, and profiling data. Includes GitHub PR performance analyzer, function analysis service, and profiling analysis system.
Home-page: https://github.com/redis/redopt
License: MIT
Keywords: redis,performance,profiling,ai,analysis,benchmarks
Author: Filipe Oliveira
Author-email: filipe@redis.com
Requires-Python: >=3.10,<4.0
Classifier: Development Status :: 4 - Beta
Classifier: Intended Audience :: Developers
Classifier: License :: OSI Approved :: MIT License
Classifier: Programming Language :: Python :: 3
Classifier: Programming Language :: Python :: 3.10
Classifier: Programming Language :: Python :: 3.11
Classifier: Programming Language :: Python :: 3.12
Classifier: Topic :: Software Development :: Libraries :: Python Modules
Classifier: Topic :: Software Development :: Quality Assurance
Classifier: Topic :: System :: Benchmark
Requires-Dist: PyGithub (>=1.59.1,<2.0.0)
Requires-Dist: clang (>=20.1.5,<21.0.0)
Requires-Dist: config (>=0.5.1,<0.6.0)
Requires-Dist: fastapi (>=0.116.1,<0.117.0)
Requires-Dist: libclang (>=18.1.1,<19.0.0)
Requires-Dist: mcp[cli] (>=1.11.0,<2.0.0)
Requires-Dist: networkx (<3.5)
Requires-Dist: numpy (<2.0)
Requires-Dist: openai (>=1.3.0,<2.0.0)
Requires-Dist: openai-agents (>=0.1.0,<0.2.0)
Requires-Dist: pydantic (>=2.11.7,<3.0.0)
Requires-Dist: pydantic-settings (>=2.10.1,<3.0.0)
Requires-Dist: python-dotenv (>=1.0.0,<2.0.0)
Requires-Dist: pyyaml (>=6.0.1,<7.0.0)
Requires-Dist: redis[hiredis] (>=6.2.0,<7.0.0)
Requires-Dist: scikit-learn (<1.5)
Requires-Dist: tqdm (>=4.67.1,<5.0.0)
Requires-Dist: uvicorn (>=0.35.0,<0.36.0)
Project-URL: Documentation, https://github.com/redis/redopt#readme
Project-URL: Repository, https://github.com/redis/redopt
